domino/__init__.py
domino/gui.py
domino/registry.py
domino/utils.py
domino/version.py
domino/_describe/__init__.py
domino/_describe/generate.py
domino/_embed/__init__.py
domino/_embed/bit.py
domino/_embed/clip.py
domino/_embed/encoder.py
domino/_embed/utils.py
domino/_slice/__init__.py
domino/_slice/abstract.py
domino/_slice/domino.py
domino/_slice/spotlight.py
domino/eval/__init__.py
domino/eval/train.py
domino/eval/utils.py
domino-0.1.5.dist-info/LICENSE
domino-0.1.5.dist-info/METADATA
domino-0.1.5.dist-info/WHEEL
domino-0.1.5.dist-info/top_level.txt
domino-0.1.5.dist-info/RECORD
