Metadata-Version: 2.1
Name: domino
Version: 0.1.5
Summary: UNKNOWN
Home-page: UNKNOWN
Author: https://github.com/HazyResearch/domino
Author-email: eyuboglu@stanford.edu
License: Apache 2.0
Platform: UNKNOWN
Classifier: Programming Language :: Python
Classifier: Programming Language :: Python :: 3
Classifier: Programming Language :: Python :: 3.7
Classifier: Programming Language :: Python :: 3.8
Classifier: Programming Language :: Python :: 3.9
Classifier: Topic :: Scientific/Engineering :: Artificial Intelligence
Requires-Python: >=3.8.6
Requires-Dist: meerkat-ml[ml]
Requires-Dist: pandas
Requires-Dist: numpy (>=1.18.0)
Requires-Dist: tqdm (>=4.49.0)
Requires-Dist: scikit-learn (==0.24.2)
Requires-Dist: ipywidgets
Requires-Dist: seaborn
Requires-Dist: torch
Requires-Dist: torchvision
Requires-Dist: ftfy
Requires-Dist: regex
Provides-Extra: dev
Requires-Dist: black (==21.5b0) ; extra == 'dev'
Requires-Dist: isort (>=5.7.0) ; extra == 'dev'
Requires-Dist: autoflake ; extra == 'dev'
Requires-Dist: flake8 (>=3.8.4) ; extra == 'dev'
Requires-Dist: mypy (>=0.9) ; extra == 'dev'
Requires-Dist: docformatter (>=1.4) ; extra == 'dev'
Requires-Dist: pytest-cov (>=2.10.1) ; extra == 'dev'
Requires-Dist: sphinx-rtd-theme (>=0.5.1) ; extra == 'dev'
Requires-Dist: nbsphinx (>=0.8.0) ; extra == 'dev'
Requires-Dist: recommonmark (>=0.7.1) ; extra == 'dev'
Requires-Dist: parameterized ; extra == 'dev'
Requires-Dist: pre-commit (>=2.9.3) ; extra == 'dev'
Requires-Dist: sphinx-autobuild ; extra == 'dev'
Requires-Dist: furo ; extra == 'dev'
Provides-Extra: eval
Requires-Dist: pytorch-lightning ; extra == 'eval'
Requires-Dist: dcbench ; extra == 'eval'
Provides-Extra: text
Requires-Dist: transformers ; extra == 'text'
Requires-Dist: nltk ; extra == 'text'
